lapa_classic/__init__.py
lapa_classic/__main__.py
lapa_classic/_cli.py
lapa_classic/counter.py
lapa_classic/naf.py
lapa_classic/sampify.py
lapa_ng/__init__.py
lapa_ng/__main__.py
lapa_ng/_cli.py
lapa_ng/classic.py
lapa_ng/factory.py
lapa_ng/naf.py
lapa_ng/phonemes.py
lapa_ng/phonemes_default.csv
lapa_ng/rules_regex.py
lapa_ng/table_rules/__init__.py
lapa_ng/table_rules/_expressions.py
lapa_ng/table_rules/_io.py
lapa_ng/table_rules/_types.py
lapa_ng/table_rules/_util.py
lapa_ng/text_clean.py
lapa_ng/translator.py
lapa_ng/types.py
lapa_ng-0.1.3.dist-info/LICENSE
lapa_ng-0.1.3.dist-info/METADATA
lapa_ng-0.1.3.dist-info/WHEEL
lapa_ng-0.1.3.dist-info/entry_points.txt
lapa_ng-0.1.3.dist-info/RECORD
