Metadata-Version: 2.3
Name: lapa-ng
Version: 0.1.3
Summary: LAPA allows for converting digitised early modern Dutch theatre plays into (presumed) phonetic script (SAMPA). To achieve this, a ruleset has been created that codifies the transliteration to SAMPA. This codebase contains parsers for the rule sets (xls format), parsers for the digitised texts (naf xml) and logic to perform counts and correlations.
License: CC-BY-4.0
Author: Fieke Smitskamp
Author-email: fieke.smitskamp@gmail.com
Requires-Python: >3.10,<3.13
Classifier: License :: Other/Proprietary License
Classifier: Programming Language :: Python :: 3
Classifier: Programming Language :: Python :: 3.11
Classifier: Programming Language :: Python :: 3.12
Requires-Dist: cachetools
Requires-Dist: click (>=8.1.8,<9.0.0)
Requires-Dist: openpyxl (>=3.1.2,<4.0.0)
Requires-Dist: pandas (>=2.2.3,<3.0.0)
Requires-Dist: pyyaml (>=6.0.2,<7.0.0)
Requires-Dist: xlrd (>=2.0.1,<3.0.0)
Requires-Dist: xlwt (>=1.3.0,<2.0.0)
